text2ipa/__init__.py
text2ipa/__main__.py
text2ipa-2.1.2.dist-info/LICENSE
text2ipa-2.1.2.dist-info/METADATA
text2ipa-2.1.2.dist-info/WHEEL
text2ipa-2.1.2.dist-info/RECORD
