Metadata-Version: 2.1
Name: text2ipa
Version: 2.1.2
Summary: Convert text to IPA for English and French
Home-page: https://github.com/tquangsdh20/text2ipa
License: Apache 2.0
Author: Joseph Quang
Author-email: tquangsdh20@hcmut.edu.vn
Requires-Python: >=3.6,<4.0
Classifier: Development Status :: 5 - Production/Stable
Classifier: Intended Audience :: Education
Classifier: Intended Audience :: End Users/Desktop
Classifier: License :: OSI Approved :: Apache Software License
Classifier: License :: Other/Proprietary License
Classifier: Operating System :: OS Independent
Classifier: Programming Language :: Python :: 3
Classifier: Programming Language :: Python :: 3.6
Classifier: Programming Language :: Python :: 3.7
Classifier: Programming Language :: Python :: 3.8
Classifier: Programming Language :: Python :: 3.9
Classifier: Programming Language :: Python :: 3.10
Classifier: Programming Language :: Python :: 3.11
Requires-Dist: bs4 (>=0.0,<0.1)
Requires-Dist: requests (>=2.23,<3.0)
Project-URL: Repository, https://github.com/tquangsdh20/text2ipa
